dkamotsky.logr-1.0.10.dist-info/DESCRIPTION.rst
dkamotsky.logr-1.0.10.dist-info/LICENSE.txt
dkamotsky.logr-1.0.10.dist-info/METADATA
dkamotsky.logr-1.0.10.dist-info/RECORD
dkamotsky.logr-1.0.10.dist-info/WHEEL
dkamotsky.logr-1.0.10.dist-info/metadata.json
dkamotsky.logr-1.0.10.dist-info/top_level.txt
logr/__init__.py
logr/config.py
logr/logr.py
